exp/__init__.py
exp/document_feature.py
exp/test.py
exp/test_express_extract.py
exp/prev/__init__.py
exp/prev/features.py
exp/prev/main.py
exp/prev/project.py
exp/prev/python_packages.py
exp/prev/save_feature.py
exp/prev/vector_database.py
speedbuild/__init__.py
speedbuild/sb.py
speedbuild/agent/__init__.py
speedbuild/agent/classifier/__init__.py
speedbuild/agent/classifier/main.py
speedbuild/agent/code_chat/__init__.py
speedbuild/agent/code_chat/codebase_chat.py
speedbuild/agent/documentation/__init__.py
speedbuild/agent/documentation/doc_cache_manager.py
speedbuild/agent/documentation/doc_writer.py
speedbuild/agent/documentation/document_feature.py
speedbuild/agent/documentation/documentation.py
speedbuild/agent/documentation/get_feature_code.py
speedbuild/agent/prompts/__init__.py
speedbuild/agent/prompts/chat_system_prompt.py
speedbuild/agent/prompts/classifier_prompt.py
speedbuild/agent/rate_limiter/__init__.py
speedbuild/agent/rate_limiter/rateLimiter.py
speedbuild/agent/tools/__init__.py
speedbuild/agent/tools/break_chunk.py
speedbuild/agent/tools/execute_command.py
speedbuild/agent/tools/read_file.py
speedbuild/agent/tools/update_file.py
speedbuild/db/__init__.py
speedbuild/db/save_feature.py
speedbuild/db/relational_db/__init__.py
speedbuild/db/relational_db/features.py
speedbuild/db/relational_db/main.py
speedbuild/db/relational_db/pkg_prepopulate_data.py
speedbuild/db/relational_db/project.py
speedbuild/db/relational_db/python_packages.py
speedbuild/db/vector_db/__init__.py
speedbuild/db/vector_db/vector_database.py
speedbuild/frameworks/__init__.py
speedbuild/frameworks/django/__init__.py
speedbuild/frameworks/django/extraction/__init__.py
speedbuild/frameworks/django/extraction/extract.py
speedbuild/frameworks/django/extraction/extract_features.py
speedbuild/frameworks/django/extraction/feature_dependencies.py
speedbuild/frameworks/django/extraction/manage_urls.py
speedbuild/frameworks/django/extraction/write_dependency.py
speedbuild-0.2.dist-info/METADATA
speedbuild-0.2.dist-info/WHEEL
speedbuild-0.2.dist-info/entry_points.txt
speedbuild-0.2.dist-info/top_level.txt
speedbuild-0.2.dist-info/RECORD
