Metadata-Version: 2.4
Name: speedbuild
Version: 0.2
Summary: Extracts, adapts, and deploys battle-tested features from existing codebases to new projects—complete with all dependencies, configurations, and framework integrations.
Requires-Dist: pyyaml
Requires-Dist: esprima
Requires-Dist: textual
Requires-Dist: readchar
Requires-Dist: chromadb
Requires-Dist: langgraph
Requires-Dist: langchain
Requires-Dist: django
Dynamic: description
Dynamic: description-content-type
Dynamic: requires-dist
Dynamic: summary
